odoo/addons/queued_purchase_notify/README.rst
odoo/addons/queued_purchase_notify/__init__.py
odoo/addons/queued_purchase_notify/__manifest__.py
odoo/addons/queued_purchase_notify/i18n/es.po
odoo/addons/queued_purchase_notify/models/__init__.py
odoo/addons/queued_purchase_notify/models/purchase_activity_notify.py
odoo/addons/queued_purchase_notify/models/purchase_log_note_notify.py
odoo/addons/queued_purchase_notify/models/purchase_mail_notify.py
odoo/addons/queued_purchase_notify/models/purchase_notify_mixin.py
odoo/addons/queued_purchase_notify/models/purchase_order.py
odoo/addons/queued_purchase_notify/models/purchase_order_type.py
odoo/addons/queued_purchase_notify/readme/CONFIGURE.md
odoo/addons/queued_purchase_notify/readme/CONTRIBUTORS.md
odoo/addons/queued_purchase_notify/readme/DESCRIPTION.md
odoo/addons/queued_purchase_notify/readme/ROADMAP.md
odoo/addons/queued_purchase_notify/security/ir.model.access.csv
odoo/addons/queued_purchase_notify/security/queued_purchase_notify_security.xml
odoo/addons/queued_purchase_notify/static/description/icon.png
odoo/addons/queued_purchase_notify/static/description/index.html
odoo/addons/queued_purchase_notify/tests/__init__.py
odoo/addons/queued_purchase_notify/tests/test_queued_purchase_notify.py
odoo/addons/queued_purchase_notify/views/purchase_order.xml
odoo/addons/queued_purchase_notify/views/view_purchase_order_type_form.xml
odoo_addon_queued_purchase_notify-17.0.1.1.0.dist-info/METADATA
odoo_addon_queued_purchase_notify-17.0.1.1.0.dist-info/WHEEL
odoo_addon_queued_purchase_notify-17.0.1.1.0.dist-info/top_level.txt
odoo_addon_queued_purchase_notify-17.0.1.1.0.dist-info/RECORD
